pyaqcv/__init__.py
pyaqcv/_pyaqcv.pyd
pyaqcv/aqcv.dll
pyaqcv/geometry.dll
pyaqcv/libomp140.x86_64.dll
pyaqcv/opencv_world3411.dll
pyaqcv/pyaqcv.py
pyaqcv-1.1.43.dist-info/LICENSE.txt
pyaqcv-1.1.43.dist-info/METADATA
pyaqcv-1.1.43.dist-info/WHEEL
pyaqcv-1.1.43.dist-info/top_level.txt
pyaqcv-1.1.43.dist-info/RECORD
